mlexhibit/__init__.py
mlexhibit/EDA/EDA.py
mlexhibit/EDA/__init__.py
mlexhibit/EDA/utils.py
mlexhibit/features/__init__.py
mlexhibit/features/features.py
mlexhibit/hypbench/__init__.py
mlexhibit/hypbench/hypbench.py
mlexhibit/imbench/__init__.py
mlexhibit/imbench/imbench.py
mlexhibit/theory/__init__.py
mlexhibit/theory/theory.py
mlexhibit-0.0.2.dist-info/LICENSE
mlexhibit-0.0.2.dist-info/METADATA
mlexhibit-0.0.2.dist-info/WHEEL
mlexhibit-0.0.2.dist-info/top_level.txt
mlexhibit-0.0.2.dist-info/RECORD
