Metadata-Version: 2.1
Name: mlexhibit
Version: 0.0.2
Summary: A high-level light-weight library for exhibiting data and machine learning analytics.
Home-page: https://mlexhibit.readthedocs.io/
Author: Essam W., Mohamed S., Mariem M., Marim N.
Author-email: essamwisam@outlook.com
License: GPLv3
Platform: UNKNOWN
Classifier: Intended Audience :: Developers
Classifier: License :: OSI Approved :: MIT License
Classifier: Programming Language :: Python
Classifier: Programming Language :: Python :: 3
Classifier: Programming Language :: Python :: 3.6
Classifier: Programming Language :: Python :: 3.7
Classifier: Programming Language :: Python :: 3.8
Classifier: Programming Language :: Python :: 3.9
Classifier: Operating System :: OS Independent
License-File: LICENSE
Requires-Dist: matplotlib (>=3.5.2)
Requires-Dist: numpy (>=1.22.4)
Requires-Dist: pandas (>=1.4.2)
Requires-Dist: scikit-learn (>=1.2.2)
Requires-Dist: scipy (>=1.7.3)
Requires-Dist: seaborn (>=0.11.2)
